itk/NDRegPython.py
itk/_NDRegPython.pyd
itk/itkMetamorphosisImageRegistrationMethodv4Python.py
itk/itkTimeVaryingVelocityFieldSemiLagrangianTransformPython.py
itk/itkWrapExtrapolateImageFunctionPython.py
itk/Configuration/NDRegConfig.py
itk/Configuration/NDReg_snake_case.py
itk_ndreg-0.2.1.dist-info/LICENSE
itk_ndreg-0.2.1.dist-info/METADATA
itk_ndreg-0.2.1.dist-info/WHEEL
itk_ndreg-0.2.1.dist-info/top_level.txt
itk_ndreg-0.2.1.dist-info/RECORD
