Metadata-Version: 2.1
Name: itk-ndreg
Version: 0.2.1
Summary: This is the Neurodata open-source Python package that performs affine and deformable (LDDMM) image registration.
Home-page: https://itk.org/
Author: Neurodata
Author-email: vikramc@jhmi.edu
License: Apache
Download-URL: https://github.com/InsightSoftwareConsortium/ITKNDReg
Keywords: ITK InsightToolkit
Platform: UNKNOWN
Classifier: License :: OSI Approved :: Apache Software License
Classifier: Programming Language :: Python
Classifier: Programming Language :: C++
Classifier: Development Status :: 4 - Beta
Classifier: Intended Audience :: Developers
Classifier: Intended Audience :: Education
Classifier: Intended Audience :: Healthcare Industry
Classifier: Intended Audience :: Science/Research
Classifier: Topic :: Scientific/Engineering
Classifier: Topic :: Scientific/Engineering :: Medical Science Apps.
Classifier: Topic :: Scientific/Engineering :: Information Analysis
Classifier: Topic :: Software Development :: Libraries
Classifier: Operating System :: Android
Classifier: Operating System :: Microsoft :: Windows
Classifier: Operating System :: POSIX
Classifier: Operating System :: Unix
Classifier: Operating System :: MacOS
Requires-Dist: itk (>=5.2rc3)
